Metadata-Version: 1.1
Name: gelb
Version: 0.11
Summary: Compiler for the GeLB Description (GD) programming language
Home-page: http://github.com/dchirila/gelb
Author: Dragos B. Chirila
Author-email: dchirila@gmail.com
License: MIT
Keywords: LB LBM CFD compilers fluid-dynamics
Platform: UNKNOWN
Classifier: Development Status :: 3 - Alpha
Classifier: License :: OSI Approved :: MIT License
Classifier: Programming Language :: Python :: 3.5
Classifier: Topic :: Software Development :: Code Generators
Classifier: Topic :: Software Development :: Compilers
Classifier: Topic :: Scientific/Engineering :: Physics
Classifier: Topic :: Scientific/Engineering :: Mathematics
